lowDB.py
lowDB-0.0.1.dist-info/LICENSE
lowDB-0.0.1.dist-info/METADATA
lowDB-0.0.1.dist-info/WHEEL
lowDB-0.0.1.dist-info/top_level.txt
lowDB-0.0.1.dist-info/RECORD
