Metadata-Version: 2.1
Name: lowDB
Version: 0.0.1
Summary: A simple package to convert a local JSON file into a NoSQL db and use for small projects
Home-page: UNKNOWN
Author: Iresharma
License: UNKNOWN
Platform: UNKNOWN
Classifier: Programming Language :: Python :: 3
Classifier: License :: OSI Approved :: MIT License
Classifier: Operating System :: OS Independent
Requires-Python: >=3.6
License-File: LICENSE
